{"title": "\u5c71\u672c\u30a2\u30c3\u30c8\u30db\u30fc\u30e0", "id": "1267432", "stickers": [{"body": "10841744", "url": "mxc://matrix.amane.moe/xajNAXnYabUkPgRKQnCpZNYb", "info": {"w": 185, "h": 160, "size": 31169, "mimetype": "image/png", "thumbnail_url": "mxc://matrix.amane.moe/xajNAXnYabUkPgRKQnCpZNYb", "thumbnail_info": {"w": 185, "h": 160, "size": 31169, "mimetype": "image/png"}}, "msgtype": "m.sticker", "id": "sha256:86ab45a0c99cba8a066564fc9a1f5715ee204fc4c5a29c22d69dc057a55096bd"}, {"body": "10841745", "url": "mxc://matrix.amane.moe/GvcaAlAKGTrcxulsKyPPlALf", "info": {"w": 185, "h": 160, "size": 35469, "mimetype": "image/png", "thumbnail_url": "mxc://matrix.amane.moe/GvcaAlAKGTrcxulsKyPPlALf", "thumbnail_info": {"w": 185, "h": 160, "size": 35469, "mimetype": "image/png"}}, "msgtype": "m.sticker", "id": "sha256:5c37422fe5ad16b4bf256f4c067ac6329124475c0e64ce44793c7c1633f108e9"}, {"body": "10841746", "url": "mxc://matrix.amane.moe/VwSgMChJrQReAdtAvTxtffkN", "info": {"w": 185, "h": 160, "size": 19353, "mimetype": "image/png", "thumbnail_url": "mxc://matrix.amane.moe/VwSgMChJrQReAdtAvTxtffkN", "thumbnail_info": {"w": 185, "h": 160, "size": 19353, "mimetype": "image/png"}}, "msgtype": "m.sticker", "id": "sha256:829eacb7c7f2f518692e046e5a49ba9e2281a0507f83be82a8ca5ffc786f50db"}, {"body": "10841747", "url": "mxc://matrix.amane.moe/sqGZJRvaDcjhbEdrzoBBafSn", "info": {"w": 185, "h": 160, "size": 21987, "mimetype": "image/png", "thumbnail_url": "mxc://matrix.amane.moe/sqGZJRvaDcjhbEdrzoBBafSn", "thumbnail_info": {"w": 185, "h": 160, "size": 21987, "mimetype": "image/png"}}, "msgtype": "m.sticker", "id": "sha256:36789449a52d04b295c25ce3c8585383701fc5cd6cfd1d7f8d0271bc5054d941"}, {"body": "10841748", "url": "mxc://matrix.amane.moe/tSGNkqXZDkIMMaZkmITImhge", "info": {"w": 185, "h": 160, "size": 29967, "mimetype": "image/png", "thumbnail_url": "mxc://matrix.amane.moe/tSGNkqXZDkIMMaZkmITImhge", "thumbnail_info": {"w": 185, "h": 160, "size": 29967, "mimetype": "image/png"}}, "msgtype": "m.sticker", "id": "sha256:4bf8454638027d7a0e4182e44ee7f14da366cdbd0fe0f70818ccf95cb3605208"}, {"body": "10841749", "url": "mxc://matrix.amane.moe/kMyWRHyEndPVHECCAMZaojtR", "info": {"w": 185, "h": 160, "size": 32312, "mimetype": "image/png", "thumbnail_url": "mxc://matrix.amane.moe/kMyWRHyEndPVHECCAMZaojtR", "thumbnail_info": {"w": 185, "h": 160, "size": 32312, "mimetype": "image/png"}}, "msgtype": "m.sticker", "id": "sha256:a8cb44528c1d87c078aebacab5dfa7f54446c964bf7acb4e06cafd81e7a707cb"}, {"body": "10841750", "url": "mxc://matrix.amane.moe/EiLAWnxgGrPtMWkdyOakfsOw", "info": {"w": 185, "h": 160, "size": 27855, "mimetype": "image/png", "thumbnail_url": "mxc://matrix.amane.moe/EiLAWnxgGrPtMWkdyOakfsOw", "thumbnail_info": {"w": 185, "h": 160, "size": 27855, "mimetype": "image/png"}}, "msgtype": "m.sticker", "id": "sha256:945d774d25a06647f8a3dc520cb0955f5ce2f19283dfc8f6cd1f61466ce9d39a"}, {"body": "10841751", "url": "mxc://matrix.amane.moe/iiqFYuSLEXwOLTOETkLEesIK", "info": {"w": 185, "h": 160, "size": 46181, "mimetype": "image/png", "thumbnail_url": "mxc://matrix.amane.moe/iiqFYuSLEXwOLTOETkLEesIK", "thumbnail_info": {"w": 185, "h": 160, "size": 46181, "mimetype": "image/png"}}, "msgtype": "m.sticker", "id": "sha256:ce00284d27a847af941dcccdf1c32ae777e3d96a2bee2dac1b1f750a4e8f5914"}, {"body": "10841752", "url": "mxc://matrix.amane.moe/UuirpgICXBDZxvXwgQBfTVjS", "info": {"w": 185, "h": 160, "size": 34757, "mimetype": "image/png", "thumbnail_url": "mxc://matrix.amane.moe/UuirpgICXBDZxvXwgQBfTVjS", "thumbnail_info": {"w": 185, "h": 160, "size": 34757, "mimetype": "image/png"}}, "msgtype": "m.sticker", "id": "sha256:9e2e3b09b1e5682b8af941b2ccd539de540eb45cc5c343e9f15300e76316fe2e"}, {"body": "10841753", "url": "mxc://matrix.amane.moe/WgVwOTMrHFlSRyHiqgSjCeGz", "info": {"w": 185, "h": 160, "size": 21626, "mimetype": "image/png", "thumbnail_url": "mxc://matrix.amane.moe/WgVwOTMrHFlSRyHiqgSjCeGz", "thumbnail_info": {"w": 185, "h": 160, "size": 21626, "mimetype": "image/png"}}, "msgtype": "m.sticker", "id": "sha256:3d9d897fa819559ff3afc9e41f42932055aa5e374a3b96fe17316963f2db35a8"}, {"body": "10841754", "url": "mxc://matrix.amane.moe/SIYBUERSPocFTakodPbDKKOs", "info": {"w": 185, "h": 160, "size": 42754, "mimetype": "image/png", "thumbnail_url": "mxc://matrix.amane.moe/SIYBUERSPocFTakodPbDKKOs", "thumbnail_info": {"w": 185, "h": 160, "size": 42754, "mimetype": "image/png"}}, "msgtype": "m.sticker", "id": "sha256:3ac398d4684dbe950fc7754946df81cd84f4e8f264aebb18ebcb48ca1fd60985"}, {"body": "10841755", "url": "mxc://matrix.amane.moe/FeIHBaoVsBvCESBPZtwSBvSw", "info": {"w": 185, "h": 160, "size": 52564, "mimetype": "image/png", "thumbnail_url": "mxc://matrix.amane.moe/FeIHBaoVsBvCESBPZtwSBvSw", "thumbnail_info": {"w": 185, "h": 160, "size": 52564, "mimetype": "image/png"}}, "msgtype": "m.sticker", "id": "sha256:2264cc1a6926102003960a5898b1001c21df400ca908d94e249febee8b5df905"}, {"body": "10841756", "url": "mxc://matrix.amane.moe/sFFOQbGyEgXAVNXvFmPKWxpa", "info": {"w": 185, "h": 160, "size": 15963, "mimetype": "image/png", "thumbnail_url": "mxc://matrix.amane.moe/sFFOQbGyEgXAVNXvFmPKWxpa", "thumbnail_info": {"w": 185, "h": 160, "size": 15963, "mimetype": "image/png"}}, "msgtype": "m.sticker", "id": "sha256:1c36b5c5a6d52cadd12b829f93564ccc7ee5fc1e84d0f715b34fd9e045863f09"}, {"body": "10841757", "url": "mxc://matrix.amane.moe/gpgMAJibCshuzaLDodzKKvdH", "info": {"w": 185, "h": 160, "size": 16773, "mimetype": "image/png", "thumbnail_url": "mxc://matrix.amane.moe/gpgMAJibCshuzaLDodzKKvdH", "thumbnail_info": {"w": 185, "h": 160, "size": 16773, "mimetype": "image/png"}}, "msgtype": "m.sticker", "id": "sha256:153495fcd8eaa0131433365e36700e8fcd46e68f93aa72149f96e4f6970c5207"}, {"body": "10841758", "url": "mxc://matrix.amane.moe/dFhWYsynRnqaMcSYyUjYMAri", "info": {"w": 185, "h": 160, "size": 14580, "mimetype": "image/png", "thumbnail_url": "mxc://matrix.amane.moe/dFhWYsynRnqaMcSYyUjYMAri", "thumbnail_info": {"w": 185, "h": 160, "size": 14580, "mimetype": "image/png"}}, "msgtype": "m.sticker", "id": "sha256:53b5cf8cd774284ad49b9c1114095ae278236c9952f32b228f156105c03c6580"}, {"body": "10841759", "url": "mxc://matrix.amane.moe/QaUWTJVFQrWpARekrTpTBcJi", "info": {"w": 185, "h": 160, "size": 32141, "mimetype": "image/png", "thumbnail_url": "mxc://matrix.amane.moe/QaUWTJVFQrWpARekrTpTBcJi", "thumbnail_info": {"w": 185, "h": 160, "size": 32141, "mimetype": "image/png"}}, "msgtype": "m.sticker", "id": "sha256:03083bda0ffd5e5f4be18157bbcee1b079be394bb4cb14c31feb2ddc2a8efb8e"}, {"body": "10841760", "url": "mxc://matrix.amane.moe/gWCXQeHfayWhKHtOJQZARiFV", "info": {"w": 185, "h": 160, "size": 21397, "mimetype": "image/png", "thumbnail_url": "mxc://matrix.amane.moe/gWCXQeHfayWhKHtOJQZARiFV", "thumbnail_info": {"w": 185, "h": 160, "size": 21397, "mimetype": "image/png"}}, "msgtype": "m.sticker", "id": "sha256:89ea80fde858c66866748dc6971bb58ea9f82adc672e3745376b4591998b0f61"}, {"body": "10841761", "url": "mxc://matrix.amane.moe/DZKZEgFKrQwBFCyfvkNsoLhE", "info": {"w": 185, "h": 160, "size": 19338, "mimetype": "image/png", "thumbnail_url": "mxc://matrix.amane.moe/DZKZEgFKrQwBFCyfvkNsoLhE", "thumbnail_info": {"w": 185, "h": 160, "size": 19338, "mimetype": "image/png"}}, "msgtype": "m.sticker", "id": "sha256:34dc65f952d66000842d788d8450ecb9bc7c53f889b684b79d60f001d76c7d3a"}, {"body": "10841762", "url": "mxc://matrix.amane.moe/NTqnkWOXOaBorgeHgCEKRHig", "info": {"w": 185, "h": 160, "size": 21753, "mimetype": "image/png", "thumbnail_url": "mxc://matrix.amane.moe/NTqnkWOXOaBorgeHgCEKRHig", "thumbnail_info": {"w": 185, "h": 160, "size": 21753, "mimetype": "image/png"}}, "msgtype": "m.sticker", "id": "sha256:0f29ac9a38a866d265109addd26fcdbe2d09c0f35d2a944646458d3440d85a7f"}, {"body": "10841763", "url": "mxc://matrix.amane.moe/IunXiPApGxbwOkvXqNqZRssB", "info": {"w": 185, "h": 160, "size": 19266, "mimetype": "image/png", "thumbnail_url": "mxc://matrix.amane.moe/IunXiPApGxbwOkvXqNqZRssB", "thumbnail_info": {"w": 185, "h": 160, "size": 19266, "mimetype": "image/png"}}, "msgtype": "m.sticker", "id": "sha256:ec9866b4794883c9128c049380d624f6ba4d45be56653cd39e7c9508bf2a14ef"}, {"body": "10841764", "url": "mxc://matrix.amane.moe/quVGEHVKfAXWZoaxlKMyJEYT", "info": {"w": 185, "h": 160, "size": 21942, "mimetype": "image/png", "thumbnail_url": "mxc://matrix.amane.moe/quVGEHVKfAXWZoaxlKMyJEYT", "thumbnail_info": {"w": 185, "h": 160, "size": 21942, "mimetype": "image/png"}}, "msgtype": "m.sticker", "id": "sha256:b1d47da5fcdc49513a1ba8e32db8f59e0bcf4cbd80b5b859747fca2ddf9fd1dd"}, {"body": "10841765", "url": "mxc://matrix.amane.moe/ODNtGcTKZAPUNcerjrKnnVfm", "info": {"w": 185, "h": 160, "size": 34810, "mimetype": "image/png", "thumbnail_url": "mxc://matrix.amane.moe/ODNtGcTKZAPUNcerjrKnnVfm", "thumbnail_info": {"w": 185, "h": 160, "size": 34810, "mimetype": "image/png"}}, "msgtype": "m.sticker", "id": "sha256:275b1c057ff3c337166003f046ceca01ec362b7c7d41a9ba9d6ca0eb142ffa9d"}, {"body": "10841766", "url": "mxc://matrix.amane.moe/kbUAzGUVtGiGhCeOTvMDdkeD", "info": {"w": 185, "h": 160, "size": 18633, "mimetype": "image/png", "thumbnail_url": "mxc://matrix.amane.moe/kbUAzGUVtGiGhCeOTvMDdkeD", "thumbnail_info": {"w": 185, "h": 160, "size": 18633, "mimetype": "image/png"}}, "msgtype": "m.sticker", "id": "sha256:32cb04fbc1b57e0af32a845f77ffc7b71b4f93bc57f32b8eea25137bdd0c7105"}, {"body": "10841767", "url": "mxc://matrix.amane.moe/cALJsZfmAZJIMzEfVqSbykhA", "info": {"w": 185, "h": 160, "size": 53471, "mimetype": "image/png", "thumbnail_url": "mxc://matrix.amane.moe/cALJsZfmAZJIMzEfVqSbykhA", "thumbnail_info": {"w": 185, "h": 160, "size": 53471, "mimetype": "image/png"}}, "msgtype": "m.sticker", "id": "sha256:fdcd42570adaecd7de04675b4d848ab8d3d332ef9391a5dc846fc7a65c0250ea"}, {"body": "10841768", "url": "mxc://matrix.amane.moe/crMyrAlkNVSVHCKbKjDSFaQs", "info": {"w": 185, "h": 160, "size": 48315, "mimetype": "image/png", "thumbnail_url": "mxc://matrix.amane.moe/crMyrAlkNVSVHCKbKjDSFaQs", "thumbnail_info": {"w": 185, "h": 160, "size": 48315, "mimetype": "image/png"}}, "msgtype": "m.sticker", "id": "sha256:2ce8f9e057d2de50d208d1ab17fb3f5d52261df220976c588ca70d8553ab9583"}, {"body": "10841769", "url": "mxc://matrix.amane.moe/awxEuQOwVsYGbDfqLrpfakEB", "info": {"w": 185, "h": 160, "size": 30257, "mimetype": "image/png", "thumbnail_url": "mxc://matrix.amane.moe/awxEuQOwVsYGbDfqLrpfakEB", "thumbnail_info": {"w": 185, "h": 160, "size": 30257, "mimetype": "image/png"}}, "msgtype": "m.sticker", "id": "sha256:e17abcc7c51125edcb8fffd0b62dc95397f74fe75d0857c4f7f611b54943742c"}, {"body": "10841770", "url": "mxc://matrix.amane.moe/iUjHjdTlVjpmtHzwHmuNRSUs", "info": {"w": 185, "h": 160, "size": 16591, "mimetype": "image/png", "thumbnail_url": "mxc://matrix.amane.moe/iUjHjdTlVjpmtHzwHmuNRSUs", "thumbnail_info": {"w": 185, "h": 160, "size": 16591, "mimetype": "image/png"}}, "msgtype": "m.sticker", "id": "sha256:4e29d2ad5fac386c0ddc2b3330564ff167da3359da5631fe5b2eb9c71c12f8ab"}, {"body": "10841771", "url": "mxc://matrix.amane.moe/OzJVvbRvacloiGzVXqZKcdpK", "info": {"w": 185, "h": 160, "size": 25051, "mimetype": "image/png", "thumbnail_url": "mxc://matrix.amane.moe/OzJVvbRvacloiGzVXqZKcdpK", "thumbnail_info": {"w": 185, "h": 160, "size": 25051, "mimetype": "image/png"}}, "msgtype": "m.sticker", "id": "sha256:137a1aa5e00529faab8486c931e54457ac4cf424753dc3b20721190b125e899f"}, {"body": "10841772", "url": "mxc://matrix.amane.moe/uktfyRJHDtRoXvSiyHPikUbC", "info": {"w": 185, "h": 160, "size": 38051, "mimetype": "image/png", "thumbnail_url": "mxc://matrix.amane.moe/uktfyRJHDtRoXvSiyHPikUbC", "thumbnail_info": {"w": 185, "h": 160, "size": 38051, "mimetype": "image/png"}}, "msgtype": "m.sticker", "id": "sha256:6d15da27a14b9e4e776c1497718254b21c140418844a21d411f124af7190ceb1"}, {"body": "10841773", "url": "mxc://matrix.amane.moe/uUsDmzrGUZhCdxMDLeyqwrcb", "info": {"w": 185, "h": 160, "size": 17782, "mimetype": "image/png", "thumbnail_url": "mxc://matrix.amane.moe/uUsDmzrGUZhCdxMDLeyqwrcb", "thumbnail_info": {"w": 185, "h": 160, "size": 17782, "mimetype": "image/png"}}, "msgtype": "m.sticker", "id": "sha256:1da64f563ce016acb79022ecaa4edb5b81ec576b24de6c57fa0f6b0ef34f3bbf"}, {"body": "10841774", "url": "mxc://matrix.amane.moe/XXHUOmoczLKuucfybKpmAAYI", "info": {"w": 185, "h": 160, "size": 14751, "mimetype": "image/png", "thumbnail_url": "mxc://matrix.amane.moe/XXHUOmoczLKuucfybKpmAAYI", "thumbnail_info": {"w": 185, "h": 160, "size": 14751, "mimetype": "image/png"}}, "msgtype": "m.sticker", "id": "sha256:a53897de6c657371c8ff4a0df011e524fb7a35a2d87d557821d813d1c2eb4203"}, {"body": "10841775", "url": "mxc://matrix.amane.moe/QmJdzeWDrYCXlnsfVWjAokLh", "info": {"w": 185, "h": 160, "size": 18252, "mimetype": "image/png", "thumbnail_url": "mxc://matrix.amane.moe/QmJdzeWDrYCXlnsfVWjAokLh", "thumbnail_info": {"w": 185, "h": 160, "size": 18252, "mimetype": "image/png"}}, "msgtype": "m.sticker", "id": "sha256:b6cc99f15568e83565a81847cf82b3a6909274176598a7cf230e7e94c5872f1e"}, {"body": "10841776", "url": "mxc://matrix.amane.moe/deNUQQnybeMwZcJkEtWKEGLC", "info": {"w": 185, "h": 160, "size": 13014, "mimetype": "image/png", "thumbnail_url": "mxc://matrix.amane.moe/deNUQQnybeMwZcJkEtWKEGLC", "thumbnail_info": {"w": 185, "h": 160, "size": 13014, "mimetype": "image/png"}}, "msgtype": "m.sticker", "id": "sha256:1430d5c4efe895a0b4b8efd4c237124eb1405e3e5432e2cfb62999ed78facfc8"}, {"body": "10841777", "url": "mxc://matrix.amane.moe/CaHyUDvmKynDbcyijYROAodt", "info": {"w": 185, "h": 160, "size": 15447, "mimetype": "image/png", "thumbnail_url": "mxc://matrix.amane.moe/CaHyUDvmKynDbcyijYROAodt", "thumbnail_info": {"w": 185, "h": 160, "size": 15447, "mimetype": "image/png"}}, "msgtype": "m.sticker", "id": "sha256:2feaa7c1c3aa7a005c636468932a2f915cf771ebf0bf31a53a8a0c0c981f7e73"}, {"body": "10841778", "url": "mxc://matrix.amane.moe/hefonywRRvnVXlBqGMlxdtdj", "info": {"w": 185, "h": 160, "size": 24127, "mimetype": "image/png", "thumbnail_url": "mxc://matrix.amane.moe/hefonywRRvnVXlBqGMlxdtdj", "thumbnail_info": {"w": 185, "h": 160, "size": 24127, "mimetype": "image/png"}}, "msgtype": "m.sticker", "id": "sha256:e6a82d5e16a846c1ee87264433a012675547c95d5c450de203de88fcf711891c"}, {"body": "10841779", "url": "mxc://matrix.amane.moe/hFgJuLapcOZWhMKEyhBouWiQ", "info": {"w": 185, "h": 160, "size": 20465, "mimetype": "image/png", "thumbnail_url": "mxc://matrix.amane.moe/hFgJuLapcOZWhMKEyhBouWiQ", "thumbnail_info": {"w": 185, "h": 160, "size": 20465, "mimetype": "image/png"}}, "msgtype": "m.sticker", "id": "sha256:bb74872abeb6beed4581353ee7e06ba1f3330a24f72ffaf4e448e88b1901e701"}, {"body": "10841780", "url": "mxc://matrix.amane.moe/CnuWbGtLenWeZzhoOwTpProz", "info": {"w": 185, "h": 160, "size": 30721, "mimetype": "image/png", "thumbnail_url": "mxc://matrix.amane.moe/CnuWbGtLenWeZzhoOwTpProz", "thumbnail_info": {"w": 185, "h": 160, "size": 30721, "mimetype": "image/png"}}, "msgtype": "m.sticker", "id": "sha256:dc5b43e1beca521d5ae15a6697f136551ddf4c5facdf774be9b12aacd30ebb1b"}, {"body": "10841781", "url": "mxc://matrix.amane.moe/EQGgHoplJOPlbXCuuejgIIVu", "info": {"w": 185, "h": 160, "size": 36877, "mimetype": "image/png", "thumbnail_url": "mxc://matrix.amane.moe/EQGgHoplJOPlbXCuuejgIIVu", "thumbnail_info": {"w": 185, "h": 160, "size": 36877, "mimetype": "image/png"}}, "msgtype": "m.sticker", "id": "sha256:fb83e638996900cd49972e90b2d2c7fe2b53d259d1a90b246fae48dbf596bd0f"}, {"body": "10841782", "url": "mxc://matrix.amane.moe/zTpoioohztrxVcpdqvPPfLpc", "info": {"w": 185, "h": 160, "size": 25150, "mimetype": "image/png", "thumbnail_url": "mxc://matrix.amane.moe/zTpoioohztrxVcpdqvPPfLpc", "thumbnail_info": {"w": 185, "h": 160, "size": 25150, "mimetype": "image/png"}}, "msgtype": "m.sticker", "id": "sha256:91d00d99bb882944d84df2c46edc98db65161efb98f14580781da14dccf7181e"}, {"body": "10841783", "url": "mxc://matrix.amane.moe/bSiHhtSkFzpZYoMhDsqSRyIG", "info": {"w": 185, "h": 160, "size": 21110, "mimetype": "image/png", "thumbnail_url": "mxc://matrix.amane.moe/bSiHhtSkFzpZYoMhDsqSRyIG", "thumbnail_info": {"w": 185, "h": 160, "size": 21110, "mimetype": "image/png"}}, "msgtype": "m.sticker", "id": "sha256:e940eb5f4753e4d428698555aafa0aba619c660e27e82cca4a049ce32eccb0a0"}]}